{
  "source": "instagram",
  "gender": "women",
  "age_bucket": "14-17",
  "total_items": 10,
  "scraped_at": "2025-10-10T17:23:03.508312",
  "content": [
    {
      "id": "instagram_women_14-17_0",
      "title": "Finally got the courage to tell my best friend how...",
      "text": "Finally got the courage to tell my best friend how I really feel\n\n#highschoolstories #teenlife #highschool",
      "url": "https://www.instagram.com/p/mock0/",
      "author": "user_0",
      "likes": 500,
      "comments": 20,
      "views": 2000,
      "hashtag": "highschoolstories",
      "created_at": "2025-10-10T17:23:03.508064",
      "source": "instagram"
    },
    {
      "id": "instagram_women_14-17_1",
      "title": "My parents just told me we're moving across the co...",
      "text": "My parents just told me we're moving across the country\n\n#highschoolstories #teenlife #highschool",
      "url": "https://www.instagram.com/p/mock1/",
      "author": "user_1",
      "likes": 600,
      "comments": 25,
      "views": 2200,
      "hashtag": "teenlife",
      "created_at": "2025-10-10T17:23:03.508078",
      "source": "instagram"
    },
    {
      "id": "instagram_women_14-17_2",
      "title": "I overheard my teacher talking about me and I wish...",
      "text": "I overheard my teacher talking about me and I wish I hadn't\n\n#highschoolstories #teenlife #highschool",
      "url": "https://www.instagram.com/p/mock2/",
      "author": "user_2",
      "likes": 700,
      "comments": 30,
      "views": 2400,
      "hashtag": "highschool",
      "created_at": "2025-10-10T17:23:03.508083",
      "source": "instagram"
    },
    {
      "id": "instagram_women_14-17_3",
      "title": "Found out my boyfriend was cheating through his In...",
      "text": "Found out my boyfriend was cheating through his Instagram story\n\n#highschoolstories #teenlife #highschool",
      "url": "https://www.instagram.com/p/mock3/",
      "author": "user_3",
      "likes": 800,
      "comments": 35,
      "views": 2600,
      "hashtag": "teenproblems",
      "created_at": "2025-10-10T17:23:03.508087",
      "source": "instagram"
    },
    {
      "id": "instagram_women_14-17_4",
      "title": "My roommate is driving me crazy and I don't know w...",
      "text": "My roommate is driving me crazy and I don't know what to do\n\n#highschoolstories #teenlife #highschool",
      "url": "https://www.instagram.com/p/mock4/",
      "author": "user_4",
      "likes": 900,
      "comments": 40,
      "views": 2800,
      "hashtag": "storytime",
      "created_at": "2025-10-10T17:23:03.508090",
      "source": "instagram"
    },
    {
      "id": "instagram_women_14-17_5",
      "title": "I failed my driving test for the third time today...",
      "text": "I failed my driving test for the third time today\n\n#highschoolstories #teenlife #highschool",
      "url": "https://www.instagram.com/p/mock5/",
      "author": "user_5",
      "likes": 1000,
      "comments": 45,
      "views": 3000,
      "hashtag": "highschoolstories",
      "created_at": "2025-10-10T17:23:03.508094",
      "source": "instagram"
    },
    {
      "id": "instagram_women_14-17_6",
      "title": "Someone started a rumor about me and now everyone ...",
      "text": "Someone started a rumor about me and now everyone believes it\n\n#highschoolstories #teenlife #highschool",
      "url": "https://www.instagram.com/p/mock6/",
      "author": "user_6",
      "likes": 1100,
      "comments": 50,
      "views": 3200,
      "hashtag": "teenlife",
      "created_at": "2025-10-10T17:23:03.508097",
      "source": "instagram"
    },
    {
      "id": "instagram_women_14-17_7",
      "title": "My dog just passed away and I can't stop crying...",
      "text": "My dog just passed away and I can't stop crying\n\n#highschoolstories #teenlife #highschool",
      "url": "https://www.instagram.com/p/mock7/",
      "author": "user_7",
      "likes": 1200,
      "comments": 55,
      "views": 3400,
      "hashtag": "highschool",
      "created_at": "2025-10-10T17:23:03.508101",
      "source": "instagram"
    },
    {
      "id": "instagram_women_14-17_8",
      "title": "I accidentally sent a text to the wrong person and...",
      "text": "I accidentally sent a text to the wrong person and it was bad\n\n#highschoolstories #teenlife #highschool",
      "url": "https://www.instagram.com/p/mock8/",
      "author": "user_8",
      "likes": 1300,
      "comments": 60,
      "views": 3600,
      "hashtag": "teenproblems",
      "created_at": "2025-10-10T17:23:03.508104",
      "source": "instagram"
    },
    {
      "id": "instagram_women_14-17_9",
      "title": "My crush just asked me out and I said no by accide...",
      "text": "My crush just asked me out and I said no by accident\n\n#highschoolstories #teenlife #highschool",
      "url": "https://www.instagram.com/p/mock9/",
      "author": "user_9",
      "likes": 1400,
      "comments": 65,
      "views": 3800,
      "hashtag": "storytime",
      "created_at": "2025-10-10T17:23:03.508107",
      "source": "instagram"
    }
  ]
}